{"name":"搜索","postlist":[{"title":"爬虫项目记录--搜索引擎图片爬取(一)","slug":"log-spider-project-0","date":"2019-12-03T14:50:32.000Z","updated":"2019-12-11T09:47:06.375Z","comments":true,"path":"api/articles/log-spider-project-0.json","excerpt":null,"keywords":null,"cover":null,"content":null,"raw":null,"categories":[{"name":"工程","path":"api/categories/工程.json"}],"tags":[{"name":"爬虫","path":"api/tags/爬虫.json"},{"name":"项目","path":"api/tags/项目.json"},{"name":"设计","path":"api/tags/设计.json"},{"name":"Spider","path":"api/tags/Spider.json"},{"name":"搜索","path":"api/tags/搜索.json"}]}]}